README.txt
setup.cfg
setup.py
docs/HISTORY.txt
docs/INSTALL.txt
docs/LICENSE.GPL
docs/LICENSE.txt
easyshop/__init__.py
easyshop.checkout.egg-info/PKG-INFO
easyshop.checkout.egg-info/SOURCES.txt
easyshop.checkout.egg-info/dependency_links.txt
easyshop.checkout.egg-info/entry_points.txt
easyshop.checkout.egg-info/namespace_packages.txt
easyshop.checkout.egg-info/not-zip-safe
easyshop.checkout.egg-info/requires.txt
easyshop.checkout.egg-info/top_level.txt
easyshop/checkout/__init__.py
easyshop/checkout/configure.zcml
easyshop/checkout/adapters/__init__.py
easyshop/checkout/adapters/checkout_management.py
easyshop/checkout/adapters/configure.zcml
easyshop/checkout/browser/__init__.py
easyshop/checkout/browser/address_add.py
easyshop/checkout/browser/address_edit.py
easyshop/checkout/browser/address_form.pt
easyshop/checkout/browser/address_select.pt
easyshop/checkout/browser/address_select.py
easyshop/checkout/browser/checkout.py
easyshop/checkout/browser/configure.zcml
easyshop/checkout/browser/order_preview.pt
easyshop/checkout/browser/order_preview.py
easyshop/checkout/browser/payment.pt
easyshop/checkout/browser/payment.py
easyshop/checkout/browser/recommendation.pt
easyshop/checkout/browser/recommendation.py
easyshop/checkout/browser/shipping.pt
easyshop/checkout/browser/shipping.py
easyshop/checkout/browser/thank_you.pt
easyshop/checkout/browser/thank_you.py
easyshop/checkout/browser/user.pt
easyshop/checkout/browser/user.py