Metadata-Version: 1.0
Name: easyshop.checkout
Version: 0.1a1
Summary: Checkout process for EasyShop
Home-page: http://svn.plone.org/svn/plone/plone.example
Author: Kai Diefenbach
Author-email: kai.diefenbach@iqpp.de
License: GPL
Platform: UNKNOWN
Classifier: Framework :: Plone
Classifier: Framework :: Zope2
Classifier: Framework :: Zope3
Classifier: Programming Language :: Python
Classifier: Topic :: Software Development :: Libraries :: Python Modules
